Clinton/__init__.py
Clinton/functions/__init__.py
Clinton/functions/collections.py
Clinton/functions/function01.py
Clinton/functions/function02.py
Clinton/scripts/__init__.py
Clinton/scripts/script01.py
Clinton/scripts/script02.py
Clinton/scripts/script05.py
clinton-0.0.5.dist-info/LICENSE
clinton-0.0.5.dist-info/METADATA
clinton-0.0.5.dist-info/WHEEL
clinton-0.0.5.dist-info/top_level.txt
clinton-0.0.5.dist-info/RECORD
