Metadata-Version: 2.1
Name: clinton
Version: 0.0.5
Summary: ㅤ
Home-page: https://github.com/Clinton-Abraham
Author: Clinton-Abraham
Author-email: clintonabrahamc@gmail.com
License: MIT
Keywords: apps,python,extensions
Classifier: Natural Language :: English
Classifier: Intended Audience :: Developers
Classifier: Operating System :: OS Independent
Classifier: Programming Language :: Python :: 3.10
Classifier: Programming Language :: Python :: 3.11
Classifier: Programming Language :: Python :: 3.12
Classifier: Topic :: Software Development :: Libraries
Classifier: Topic :: Software Development :: Libraries :: Python Modules
Classifier: License :: OSI Approved :: GNU Lesser General Public License v3 (LGPLv3)
Requires-Python: ~=3.10
License-File: LICENSE
Requires-Dist: aiohttp
Requires-Dist: requests
Requires-Dist: ffmpeg-python
